pmapper/__init__.py
pmapper/customize.py
pmapper/get_pharm_counts.py
pmapper/pharmacophore.py
pmapper/smarts_features.fdef
pmapper/smarts_features.txt
pmapper/utils.py
pmapper/speedtest/__init__.py
pmapper/speedtest/confs.pkl
pmapper/speedtest/pmapper_speed_test.py
pmapper-1.1.3.dist-info/LICENSE.txt
pmapper-1.1.3.dist-info/METADATA
pmapper-1.1.3.dist-info/WHEEL
pmapper-1.1.3.dist-info/entry_points.txt
pmapper-1.1.3.dist-info/top_level.txt
pmapper-1.1.3.dist-info/RECORD
