Metadata-Version: 2.1
Name: pmapper
Version: 1.1.3
Summary: pmapper: 3D pharmacophore hashes and fingerprints
Home-page: https://github.com/DrrDom/pmapper
Author: Pavel Polishchuk
Author-email: pavel_polishchuk@ukr.net
Classifier: Programming Language :: Python :: 3
Classifier: License :: OSI Approved :: BSD License
Classifier: Operating System :: OS Independent
Classifier: Topic :: Scientific/Engineering :: Bio-Informatics
Classifier: Topic :: Scientific/Engineering :: Chemistry
Requires-Python: >=3.6
License-File: LICENSE.txt
Requires-Dist: networkx >=2
Provides-Extra: rdkit
Requires-Dist: rdkit >=2017.09 ; extra == 'rdkit'
